{
  "5010001": {
    "drop_type": 50,
    "id": 5010001,
    "link_id": 10001
  },
  "5010002": {
    "drop_type": 50,
    "id": 5010002,
    "link_id": 10002
  },
  "5010003": {
    "drop_type": 50,
    "id": 5010003,
    "link_id": 10003
  },
  "5010004": {
    "drop_type": 50,
    "id": 5010004,
    "link_id": 10004
  },
  "5010005": {
    "drop_type": 50,
    "id": 5010005,
    "link_id": 10005
  },
  "5020001": {
    "drop_type": 50,
    "id": 5020001,
    "link_id": 20001
  },
  "5020002": {
    "drop_type": 50,
    "id": 5020002,
    "link_id": 20002
  },
  "5020003": {
    "drop_type": 50,
    "id": 5020003,
    "link_id": 20003
  },
  "5020004": {
    "drop_type": 50,
    "id": 5020004,
    "link_id": 20004
  },
  "5020005": {
    "drop_type": 50,
    "id": 5020005,
    "link_id": 20005
  },
  "5030001": {
    "drop_type": 50,
    "id": 5030001,
    "link_id": 30001
  },
  "5030002": {
    "drop_type": 50,
    "id": 5030002,
    "link_id": 30002
  },
  "5030003": {
    "drop_type": 50,
    "id": 5030003,
    "link_id": 30003
  },
  "5030004": {
    "drop_type": 50,
    "id": 5030004,
    "link_id": 30004
  },
  "5030005": {
    "drop_type": 50,
    "id": 5030005,
    "link_id": 30005
  },
  "all": [
    5010001,
    5010002,
    5010003,
    5010004,
    5010005,
    5020001,
    5020002,
    5020003,
    5020004,
    5020005,
    5030001,
    5030002,
    5030003,
    5030004,
    5030005
  ]
}