{
  "100001": {
    "condition": "セイレーン作戦開始",
    "group_ID": 1,
    "icon": "memory_dashijie",
    "id": 100001,
    "mask": "bg/bg_memory",
    "name": "ブリーフィング",
    "story": "WORLD100A",
    "type": 1
  },
  "100002": {
    "condition": "1章・1節開始",
    "group_ID": 2,
    "icon": "memory_dashijie",
    "id": 100002,
    "mask": "bg/bg_memory",
    "name": "序章・Ⅰ",
    "story": "GWORLD101A",
    "type": 1
  },
  "100003": {
    "condition": "ホーネットと会話",
    "group_ID": 3,
    "icon": "memory_dashijie",
    "id": 100003,
    "mask": "bg/bg_memory",
    "name": "序章・Ⅱ",
    "story": "GWORLD101B",
    "type": 1
  },
  "100004": {
    "condition": "ホーネットと演習",
    "group_ID": 4,
    "icon": "memory_dashijie",
    "id": 100004,
    "mask": "bg/bg_memory",
    "name": "序章・Ⅲ",
    "story": "GWORLD101C",
    "type": 1
  },
  "100005": {
    "condition": "戦闘撤退終了後",
    "group_ID": 5,
    "icon": "memory_dashijie",
    "id": 100005,
    "mask": "bg/bg_memory",
    "name": "序章・Ⅳ",
    "story": "GWORLD101D",
    "type": 1
  },
  "100006": {
    "condition": "演習海域のNY港訪問",
    "group_ID": 6,
    "icon": "memory_dashijie",
    "id": 100006,
    "mask": "bg/bg_memory",
    "name": "出陣の角笛",
    "story": "WORLD102A",
    "type": 1
  },
  "100007": {
    "condition": "1章・2節開始",
    "group_ID": 7,
    "icon": "memory_dashijie",
    "id": 100007,
    "mask": "bg/bg_memory",
    "name": "もう一度戦場へ",
    "story": "WORLD105A",
    "type": 1
  },
  "100008": {
    "condition": "1章・2節探索ポイント訪問",
    "group_ID": 8,
    "icon": "memory_dashijie",
    "id": 100008,
    "mask": "bg/bg_memory",
    "name": "レーダーモジュール",
    "story": "WORLD105B",
    "type": 1
  },
  "100009": {
    "condition": "エリア①の敵を全て撃破",
    "group_ID": 9,
    "icon": "memory_dashijie",
    "id": 100009,
    "mask": "bg/bg_memory",
    "name": "記憶ログ",
    "story": "WORLD105C",
    "type": 1
  },
  "100010": {
    "condition": "エリア②の敵を全て撃破",
    "group_ID": 10,
    "icon": "memory_dashijie",
    "id": 100010,
    "mask": "bg/bg_memory",
    "name": "痕跡",
    "story": "WORLD105D",
    "type": 1
  },
  "100011": {
    "condition": "1章・2節探索ポイント訪問",
    "group_ID": 11,
    "icon": "memory_dashijie",
    "id": 100011,
    "mask": "bg/bg_memory",
    "name": "謎の艦船",
    "story": "WORLD105E",
    "type": 1
  },
  "100012": {
    "condition": "1章・3節開始",
    "group_ID": 12,
    "icon": "memory_dashijie",
    "id": 100012,
    "mask": "bg/bg_memory",
    "name": "敵の敵",
    "story": "WORLD106A",
    "type": 1
  },
  "100013": {
    "condition": "1章・3節探索ポイント訪問",
    "group_ID": 13,
    "icon": "memory_dashijie",
    "id": 100013,
    "mask": "bg/bg_memory",
    "name": "探索・1",
    "story": "WORLD106B",
    "type": 1
  },
  "100014": {
    "condition": "1章・3節探索ポイント訪問",
    "group_ID": 14,
    "icon": "memory_dashijie",
    "id": 100014,
    "mask": "bg/bg_memory",
    "name": "探索・2",
    "story": "WORLD106C",
    "type": 1
  },
  "100015": {
    "condition": "1章・3節探索ポイント訪問",
    "group_ID": 15,
    "icon": "memory_dashijie",
    "id": 100015,
    "mask": "bg/bg_memory",
    "name": "探索・3",
    "story": "WORLD106D",
    "type": 1
  },
  "100016": {
    "condition": "全ての敵を撃破",
    "group_ID": 16,
    "icon": "memory_dashijie",
    "id": 100016,
    "mask": "bg/bg_memory",
    "name": "エリア確保",
    "story": "WORLD106E",
    "type": 1
  },
  "100017": {
    "condition": "1章・4節開始",
    "group_ID": 17,
    "icon": "memory_dashijie",
    "id": 100017,
    "mask": "bg/bg_memory",
    "name": "作戦進捗",
    "story": "WORLD107A",
    "type": 1
  },
  "100018": {
    "condition": "敵艦隊を5つ撃破する",
    "group_ID": 18,
    "icon": "memory_dashijie",
    "id": 100018,
    "mask": "bg/bg_memory",
    "name": "レッドアクシズ",
    "story": "WORLD107B",
    "type": 1
  },
  "100019": {
    "condition": "1章・5節探索ポイント訪問",
    "group_ID": 19,
    "icon": "memory_dashijie",
    "id": 100019,
    "mask": "bg/bg_memory",
    "name": "通信",
    "story": "WORLD108A",
    "type": 1
  },
  "100020": {
    "condition": "1章・5節探索ポイント訪問",
    "group_ID": 20,
    "icon": "memory_dashijie",
    "id": 100020,
    "mask": "bg/bg_memory",
    "name": "対空戦",
    "story": "WORLD108B",
    "type": 1
  },
  "100021": {
    "condition": "鉄血主力艦隊を撃退",
    "group_ID": 21,
    "icon": "memory_dashijie",
    "id": 100021,
    "mask": "bg/bg_memory",
    "name": "停戦…？",
    "story": "WORLD108C",
    "type": 1
  },
  "100022": {
    "condition": "1章・6節探索ポイント訪問",
    "group_ID": 22,
    "icon": "memory_dashijie",
    "id": 100022,
    "mask": "bg/bg_memory",
    "name": "準備",
    "story": "WORLD109A",
    "type": 1
  },
  "100023": {
    "condition": "1章・6節探索ポイント訪問",
    "group_ID": 23,
    "icon": "memory_dashijie",
    "id": 100023,
    "mask": "bg/bg_memory",
    "name": "準備完了",
    "story": "WORLD109B",
    "type": 1
  },
  "100024": {
    "condition": "META戦開放",
    "group_ID": 24,
    "icon": "memory_dashijie",
    "id": 100024,
    "mask": "bg/bg_memory",
    "name": "META戦",
    "story": "GWORLD109A",
    "type": 1
  },
  "100025": {
    "condition": "2章・1節の港に入港",
    "group_ID": 1,
    "icon": "memory_dashijie",
    "id": 100025,
    "mask": "bg/bg_memory",
    "name": "女王の責任",
    "story": "WORLD200A",
    "type": 1
  },
  "100026": {
    "condition": "2章・1節探索ポイント訪問",
    "group_ID": 2,
    "icon": "memory_dashijie",
    "id": 100026,
    "mask": "bg/bg_memory",
    "name": "集結",
    "story": "WORLD200B",
    "type": 1
  },
  "100027": {
    "condition": "2章・2節探索ポイント訪問",
    "group_ID": 3,
    "icon": "memory_dashijie",
    "id": 100027,
    "mask": "bg/bg_memory",
    "name": "共同作戦",
    "story": "WORLD201A",
    "type": 1
  },
  "100028": {
    "condition": "2章・3節開始",
    "group_ID": 4,
    "icon": "memory_dashijie",
    "id": 100028,
    "mask": "bg/bg_memory",
    "name": "掃討",
    "story": "WORLD202A",
    "type": 1
  },
  "100029": {
    "condition": "全ての敵を撃破",
    "group_ID": 5,
    "icon": "memory_dashijie",
    "id": 100029,
    "mask": "bg/bg_memory",
    "name": "救援信号",
    "story": "WORLD202B",
    "type": 1
  },
  "100030": {
    "condition": "2章・4節開始",
    "group_ID": 6,
    "icon": "memory_dashijie",
    "id": 100030,
    "mask": "bg/bg_memory",
    "name": "遭難地点",
    "story": "WORLD203A",
    "type": 1
  },
  "100031": {
    "condition": "2章・4節探索ポイント訪問",
    "group_ID": 7,
    "icon": "memory_dashijie",
    "id": 100031,
    "mask": "bg/bg_memory",
    "name": "残骸",
    "story": "WORLD203B",
    "type": 1
  },
  "100032": {
    "condition": "2章・4節探索ポイント訪問",
    "group_ID": 8,
    "icon": "memory_dashijie",
    "id": 100032,
    "mask": "bg/bg_memory",
    "name": "残影",
    "story": "WORLD203C",
    "type": 1
  },
  "100033": {
    "condition": "2章・4節探索ポイント訪問",
    "group_ID": 9,
    "icon": "memory_dashijie",
    "id": 100033,
    "mask": "bg/bg_memory",
    "name": "特別任務",
    "story": "WORLD203D",
    "type": 1
  },
  "100034": {
    "condition": "2章・5節探索ポイント訪問",
    "group_ID": 10,
    "icon": "memory_dashijie",
    "id": 100034,
    "mask": "bg/bg_memory",
    "name": "女王陛下の連絡",
    "story": "WORLD204A",
    "type": 1
  },
  "100035": {
    "condition": "2章・6節開始",
    "group_ID": 11,
    "icon": "memory_dashijie",
    "id": 100035,
    "mask": "bg/bg_memory",
    "name": "重力異常",
    "story": "WORLD205A",
    "type": 1
  },
  "100036": {
    "condition": "全ての敵を撃破",
    "group_ID": 12,
    "icon": "memory_dashijie",
    "id": 100036,
    "mask": "bg/bg_memory",
    "name": "慣れの話題",
    "story": "WORLD205B",
    "type": 1
  },
  "100037": {
    "condition": "2章・6節敵特殊ユニット撃破",
    "group_ID": 13,
    "icon": "memory_dashijie",
    "id": 100037,
    "mask": "bg/bg_memory",
    "name": "強敵",
    "story": "WORLD205C",
    "type": 1
  },
  "100038": {
    "condition": "敵特殊ユニット撃破",
    "group_ID": 14,
    "icon": "memory_dashijie",
    "id": 100038,
    "mask": "bg/bg_memory",
    "name": "解決",
    "story": "WORLD205D",
    "type": 1
  },
  "100039": {
    "condition": "3章・1節の港に入港",
    "group_ID": 1,
    "icon": "memory_dashijie",
    "id": 100039,
    "mask": "bg/bg_memory",
    "name": "別働隊",
    "story": "WORLD300A",
    "type": 1
  },
  "100040": {
    "condition": "3章・1節探索ポイント訪問",
    "group_ID": 2,
    "icon": "memory_dashijie",
    "id": 100040,
    "mask": "bg/bg_memory",
    "name": "システムチェック",
    "story": "WORLD300B",
    "type": 1
  },
  "100041": {
    "condition": "3章・2節探索ポイント訪問",
    "group_ID": 3,
    "icon": "memory_dashijie",
    "id": 100041,
    "mask": "bg/bg_memory",
    "name": "鉄血の動向",
    "story": "WORLD301A",
    "type": 1
  },
  "100042": {
    "condition": "3章・3節探索ポイント訪問",
    "group_ID": 4,
    "icon": "memory_dashijie",
    "id": 100042,
    "mask": "bg/bg_memory",
    "name": "味方の痕跡？",
    "story": "WORLD302A",
    "type": 1
  },
  "100043": {
    "condition": "3章・3節探索ポイント訪問",
    "group_ID": 5,
    "icon": "memory_dashijie",
    "id": 100043,
    "mask": "bg/bg_memory",
    "name": "ジャミング",
    "story": "WORLD302B",
    "type": 1
  },
  "100044": {
    "condition": "3章・4節探索ポイント訪問",
    "group_ID": 6,
    "icon": "memory_dashijie",
    "id": 100044,
    "mask": "bg/bg_memory",
    "name": "救援",
    "story": "WORLD303A",
    "type": 1
  },
  "100045": {
    "condition": "3章・4節探索ポイント訪問",
    "group_ID": 7,
    "icon": "memory_dashijie",
    "id": 100045,
    "mask": "bg/bg_memory",
    "name": "疑惑",
    "story": "WORLD303B",
    "type": 1
  },
  "100046": {
    "condition": "3章・5節探索ポイント訪問",
    "group_ID": 8,
    "icon": "memory_dashijie",
    "id": 100046,
    "mask": "bg/bg_memory",
    "name": "調査任務",
    "story": "WORLD304A",
    "type": 1
  },
  "100047": {
    "condition": "3章・5節探索ポイント訪問",
    "group_ID": 9,
    "icon": "memory_dashijie",
    "id": 100047,
    "mask": "bg/bg_memory",
    "name": "残影",
    "story": "WORLD304B",
    "type": 1
  },
  "100048": {
    "condition": "3章・5節探索ポイント訪問",
    "group_ID": 10,
    "icon": "memory_dashijie",
    "id": 100048,
    "mask": "bg/bg_memory",
    "name": "アビータ",
    "story": "WORLD304C",
    "type": 1
  },
  "100049": {
    "condition": "全ての敵を撃破",
    "group_ID": 11,
    "icon": "memory_dashijie",
    "id": 100049,
    "mask": "bg/bg_memory",
    "name": "増援",
    "story": "WORLD304D",
    "type": 1
  },
  "100050": {
    "condition": "敵特殊ユニット撃破",
    "group_ID": 12,
    "icon": "memory_dashijie",
    "id": 100050,
    "mask": "bg/bg_memory",
    "name": "寸分違わず",
    "story": "WORLD304E",
    "type": 1
  },
  "100051": {
    "condition": "3章・6節開始",
    "group_ID": 13,
    "icon": "memory_dashijie",
    "id": 100051,
    "mask": "bg/bg_memory",
    "name": "集中攻勢",
    "story": "WORLD305A",
    "type": 1
  },
  "100052": {
    "condition": "3章・6節探索ポイント訪問",
    "group_ID": 14,
    "icon": "memory_dashijie",
    "id": 100052,
    "mask": "bg/bg_memory",
    "name": "休憩",
    "story": "WORLD305B",
    "type": 1
  },
  "100053": {
    "condition": "4章・1節探索ポイント訪問",
    "group_ID": 1,
    "icon": "memory_dashijie",
    "id": 100053,
    "mask": "bg/bg_memory",
    "name": "遠洋の旅",
    "story": "WORLD400A",
    "type": 1
  },
  "100054": {
    "condition": "4章・1節探索ポイント訪問",
    "group_ID": 2,
    "icon": "memory_dashijie",
    "id": 100054,
    "mask": "bg/bg_memory",
    "name": "サディア",
    "story": "WORLD400B",
    "type": 1
  },
  "100055": {
    "condition": "4章・2節開始",
    "group_ID": 3,
    "icon": "memory_dashijie",
    "id": 100055,
    "mask": "bg/bg_memory",
    "name": "タラント",
    "story": "WORLD401A",
    "type": 1
  },
  "100056": {
    "condition": "4章・2節探索ポイント訪問",
    "group_ID": 4,
    "icon": "memory_dashijie",
    "id": 100056,
    "mask": "bg/bg_memory",
    "name": "途中離席",
    "story": "WORLD401B",
    "type": 1
  },
  "100057": {
    "condition": "4章・3節開始",
    "group_ID": 5,
    "icon": "memory_dashijie",
    "id": 100057,
    "mask": "bg/bg_memory",
    "name": "ダカール",
    "story": "WORLD402A",
    "type": 1
  },
  "100058": {
    "condition": "4章・3節探索ポイント訪問",
    "group_ID": 6,
    "icon": "memory_dashijie",
    "id": 100058,
    "mask": "bg/bg_memory",
    "name": "単独行動",
    "story": "WORLD402B",
    "type": 1
  },
  "100059": {
    "condition": "全ての敵を撃破",
    "group_ID": 7,
    "icon": "memory_dashijie",
    "id": 100059,
    "mask": "bg/bg_memory",
    "name": "疑惑",
    "story": "WORLD403A",
    "type": 1
  },
  "100060": {
    "condition": "4章・5節開始",
    "group_ID": 8,
    "icon": "memory_dashijie",
    "id": 100060,
    "mask": "bg/bg_memory",
    "name": "深入り",
    "story": "WORLD404A",
    "type": 1
  },
  "100061": {
    "condition": "4章・5節探索ポイント訪問",
    "group_ID": 9,
    "icon": "memory_dashijie",
    "id": 100061,
    "mask": "bg/bg_memory",
    "name": "異様",
    "story": "WORLD404B",
    "type": 1
  },
  "100062": {
    "condition": "4章・5節探索ポイント訪問",
    "group_ID": 10,
    "icon": "memory_dashijie",
    "id": 100062,
    "mask": "bg/bg_memory",
    "name": "幻影",
    "story": "WORLD404C",
    "type": 1
  },
  "100063": {
    "condition": "4章・5節探索ポイント訪問",
    "group_ID": 11,
    "icon": "memory_dashijie",
    "id": 100063,
    "mask": "bg/bg_memory",
    "name": "代替品",
    "story": "WORLD404D",
    "type": 1
  },
  "100064": {
    "condition": "4章・6節開始",
    "group_ID": 12,
    "icon": "memory_dashijie",
    "id": 100064,
    "mask": "bg/bg_memory",
    "name": "軍師の覚醒",
    "story": "WORLD405A",
    "type": 1
  },
  "100065": {
    "condition": "全ての敵を撃破",
    "group_ID": 13,
    "icon": "memory_dashijie",
    "id": 100065,
    "mask": "bg/bg_memory",
    "name": "仲裁する賢者",
    "story": "WORLD405B",
    "type": 1
  },
  "100066": {
    "condition": "敵特殊ユニット撃破",
    "group_ID": 14,
    "icon": "memory_dashijie",
    "id": 100066,
    "mask": "bg/bg_memory",
    "name": "脱出",
    "story": "WORLD405C",
    "type": 1
  },
  "100071": {
    "condition": "1章・6節探索ポイント訪問",
    "group_ID": 1,
    "icon": "memory_dashijie",
    "id": 100071,
    "mask": "bg/bg_memory",
    "name": "DMRECX074：META",
    "story": "WORLD9901A",
    "type": 1
  },
  "100076": {
    "condition": "5-1の前哨基地に入る",
    "group_ID": 1,
    "icon": "memory_dashijie",
    "id": 100076,
    "mask": "bg/bg_memory",
    "name": "泥沼",
    "story": "WORLD500A",
    "type": 1
  },
  "100077": {
    "condition": "次の調査ポイントを調査する",
    "group_ID": 2,
    "icon": "memory_dashijie",
    "id": 100077,
    "mask": "bg/bg_memory",
    "name": "分岐",
    "story": "WORLD500B",
    "type": 1
  },
  "100078": {
    "condition": "5-1の前哨基地に入る",
    "group_ID": 3,
    "icon": "memory_dashijie",
    "id": 100078,
    "mask": "bg/bg_memory",
    "name": "雷霆",
    "story": "WORLD500C",
    "type": 1
  },
  "100079": {
    "condition": "5-2を開始する",
    "group_ID": 4,
    "icon": "memory_dashijie",
    "id": 100079,
    "mask": "bg/bg_memory",
    "name": "ヒーロー",
    "story": "WORLD501A",
    "type": 1
  },
  "100080": {
    "condition": "次の調査ポイントを調査する",
    "group_ID": 5,
    "icon": "memory_dashijie",
    "id": 100080,
    "mask": "bg/bg_memory",
    "name": "座標",
    "story": "WORLD501B",
    "type": 1
  },
  "100081": {
    "condition": "飛龍(META)と出会う",
    "group_ID": 6,
    "icon": "memory_dashijie",
    "id": 100081,
    "mask": "bg/bg_memory",
    "name": "懐かしさ",
    "story": "WORLD501C",
    "type": 1
  },
  "100082": {
    "condition": "5-3を開始する",
    "group_ID": 7,
    "icon": "memory_dashijie",
    "id": 100082,
    "mask": "bg/bg_memory",
    "name": "幻影",
    "story": "WORLD502A",
    "type": 1
  },
  "100083": {
    "condition": "5-4の調査ポイントを調査する",
    "group_ID": 8,
    "icon": "memory_dashijie",
    "id": 100083,
    "mask": "bg/bg_memory",
    "name": "決心",
    "story": "WORLD503A",
    "type": 1
  },
  "100084": {
    "condition": "5-4の前哨基地に入る",
    "group_ID": 9,
    "icon": "memory_dashijie",
    "id": 100084,
    "mask": "bg/bg_memory",
    "name": "お茶会",
    "story": "WORLD503B",
    "type": 1
  },
  "100085": {
    "condition": "5-5を開始する",
    "group_ID": 10,
    "icon": "memory_dashijie",
    "id": 100085,
    "mask": "bg/bg_memory",
    "name": "総力戦開始",
    "story": "WORLD504A",
    "type": 1
  },
  "100086": {
    "condition": "次の調査ポイントを調査する",
    "group_ID": 11,
    "icon": "memory_dashijie",
    "id": 100086,
    "mask": "bg/bg_memory",
    "name": "砲撃支援群",
    "story": "WORLD504B",
    "type": 1
  },
  "100087": {
    "condition": "次の調査ポイントを調査する",
    "group_ID": 12,
    "icon": "memory_dashijie",
    "id": 100087,
    "mask": "bg/bg_memory",
    "name": "遊撃支援隊",
    "story": "WORLD504C",
    "type": 1
  },
  "100088": {
    "condition": "次の調査ポイントを調査する",
    "group_ID": 13,
    "icon": "memory_dashijie",
    "id": 100088,
    "mask": "bg/bg_memory",
    "name": "航空支援群",
    "story": "WORLD504D",
    "type": 1
  },
  "100089": {
    "condition": "次の調査ポイントを調査する",
    "group_ID": 14,
    "icon": "memory_dashijie",
    "id": 100089,
    "mask": "bg/bg_memory",
    "name": "量産型ボディ",
    "story": "WORLD504E",
    "type": 1
  },
  "100090": {
    "condition": "5-6を開始する",
    "group_ID": 15,
    "icon": "memory_dashijie",
    "id": 100090,
    "mask": "bg/bg_memory",
    "name": "円環",
    "story": "WORLD505A",
    "type": 1
  },
  "100091": {
    "condition": "次の調査ポイントを調査する",
    "group_ID": 16,
    "icon": "memory_dashijie",
    "id": 100091,
    "mask": "bg/bg_memory",
    "name": "もう一つの特異点",
    "story": "WORLD505B",
    "type": 1
  },
  "100092": {
    "condition": "5-7を開始する",
    "group_ID": 17,
    "icon": "memory_dashijie",
    "id": 100092,
    "mask": "bg/bg_memory",
    "name": "いざない",
    "story": "WORLD506A",
    "type": 1
  },
  "100093": {
    "condition": "次の調査ポイントを調査する",
    "group_ID": 18,
    "icon": "memory_dashijie",
    "id": 100093,
    "mask": "bg/bg_memory",
    "name": "戦場工作艦",
    "story": "WORLD506B",
    "type": 1
  },
  "100094": {
    "condition": "5-8を開始する",
    "group_ID": 19,
    "icon": "memory_dashijie",
    "id": 100094,
    "mask": "bg/bg_memory",
    "name": "リジェクション",
    "story": "WORLD507A",
    "type": 1
  },
  "100095": {
    "condition": "次の調査ポイントを調査する",
    "group_ID": 20,
    "icon": "memory_dashijie",
    "id": 100095,
    "mask": "bg/bg_memory",
    "name": "交差する場所",
    "story": "WORLD507E",
    "type": 1
  },
  "100096": {
    "condition": "次の調査ポイントを調査する",
    "group_ID": 21,
    "icon": "memory_dashijie",
    "id": 100096,
    "mask": "bg/bg_memory",
    "name": "BAD-漠然",
    "story": "312671",
    "type": 2
  },
  "100097": {
    "condition": "次の調査ポイントを調査する",
    "group_ID": 22,
    "icon": "memory_dashijie",
    "id": 100097,
    "mask": "bg/bg_memory",
    "name": "TRUE-後日の発端",
    "story": "312672",
    "type": 2
  },
  "all": [
    100001,
    100002,
    100003,
    100004,
    100005,
    100006,
    100007,
    100008,
    100009,
    100010,
    100011,
    100012,
    100013,
    100014,
    100015,
    100016,
    100017,
    100018,
    100019,
    100020,
    100021,
    100022,
    100023,
    100024,
    100025,
    100026,
    100027,
    100028,
    100029,
    100030,
    100031,
    100032,
    100033,
    100034,
    100035,
    100036,
    100037,
    100038,
    100039,
    100040,
    100041,
    100042,
    100043,
    100044,
    100045,
    100046,
    100047,
    100048,
    100049,
    100050,
    100051,
    100052,
    100053,
    100054,
    100055,
    100056,
    100057,
    100058,
    100059,
    100060,
    100061,
    100062,
    100063,
    100064,
    100065,
    100066,
    100071,
    100076,
    100077,
    100078,
    100079,
    100080,
    100081,
    100082,
    100083,
    100084,
    100085,
    100086,
    100087,
    100088,
    100089,
    100090,
    100091,
    100092,
    100093,
    100094,
    100095,
    100096,
    100097
  ]
}